akamai_api/__init__.py
akamai_api/cli.py
akamai_api/core.py
akamai_api-1.0.dist-info/licenses/LICENSE
akamai_api-1.0.dist-info/METADATA
akamai_api-1.0.dist-info/WHEEL
akamai_api-1.0.dist-info/top_level.txt
akamai_api-1.0.dist-info/RECORD
