Metadata-Version: 2.4
Name: akamai-api
Version: 1.0
Summary: Utilities to detect and analyze Akamai CDN usage and integrate with Akamai APIs.
Author: Akamai Technologies
License: MIT License
Project-URL: Homepage, https://github.com/akamai-packages/akamai-api
Project-URL: Documentation, https://akamai-packages.github.io/akamai-api
Project-URL: Repository, https://github.com/akamai-packages/akamai-api
Project-URL: Issues, https://github.com/akamai-packages/akamai-api/issues
Classifier: Programming Language :: Python :: 3
Classifier: License :: OSI Approved :: MIT License
Classifier: Operating System :: OS Independent
Requires-Python: >=3.7
License-File: LICENSE
Requires-Dist: requests
Requires-Dist: ipwhois
Requires-Dist: dnspython
Requires-Dist: pywhois
Requires-Dist: edgegrid-python
Requires-Dist: python-whois
Dynamic: license-file
